setup.py
scripts/__init__.py
scripts/shinkansen_service.py
scripts/shinkansen_trim_crate_data.py
shinkansen/__init__.py
shinkansen/db.py
shinkansen/lock.py
shinkansen/status.py
shinkansen/config/__init__.py
shinkansen/config/defaults.py
shinkansen/data/__init__.py
shinkansen/http/__init__.py
shinkansen/http/common.py
shinkansen/http/v5.py
shinkansen/orm/__init__.py
shinkansen/orm/memredis.py
shinkansen/orm/patch/__init__.py
shinkansen/service/__init__.py
shinkansen/worker/__init__.py
shinkansen/worker/importer.py
shinkansen/worker/master.py
shinkansen/worker/pipe.py
shinkansen/worker/queuer.py
shinkansen/worker/streamer.py
shinkansen/worker/verifier.py
shinkansen/worker/exporter/__init__.py
shinkansen/worker/exporter/crate.py
shinkansen/worker/exporter/mysql.py
shinkansen_python.egg-info/PKG-INFO
shinkansen_python.egg-info/SOURCES.txt
shinkansen_python.egg-info/dependency_links.txt
shinkansen_python.egg-info/requires.txt
shinkansen_python.egg-info/top_level.txt
test/__init__.py
test/scripts/__init__.py
test/scripts/test_trim_crate_data.py
test/shinkansen/__init__.py
test/shinkansen/test_db.py
test/shinkansen/test_lock.py
test/shinkansen/test_status.py
test/shinkansen/http/__init__.py
test/shinkansen/http/test_common.py
test/shinkansen/http/test_v5.py
test/shinkansen/orm/__init__.py
test/shinkansen/orm/test_orm.py
test/shinkansen/orm/test_patch.py
test/shinkansen/worker/__init__.py
test/shinkansen/worker/test_exporter.py
test/shinkansen/worker/test_importer.py
test/shinkansen/worker/test_master.py
test/shinkansen/worker/test_pipe.py
test/shinkansen/worker/test_queuer.py
test/shinkansen/worker/test_streamer.py
test/shinkansen/worker/test_verifier.py