Metadata-Version: 1.0
Name: shinkansen-python
Version: 1.0.0
Summary: A bullet train for your data
Home-page: https://github.com/skyhigh-networks/shinkansen
Author: Justin Patrin
Author-email: jpatrin@skyhighnetworks.com
License: UNKNOWN
Platform: UNKNOWN
